[
    {
        "name": "job_id",
        "type": "STRING",
        "mode": "REQUIRED"
    },
    {
        "name": "create_ts",
        "type": "DATETIME",
        "mode": "REQUIRED"
    },
    {
        "name": "operation",
        "type": "STRING",
        "mode": "REQUIRED"
    },
    {
        "name": "result",
        "type": "JSON",
        "mode": "NULLABLE"
    },
    {
        "name": "batch_num",
        "type": "INTEGER",
        "mode": "NULLABLE"
    },
    {
        "name": "batch_len",
        "type": "INTEGER",
        "mode": "NULLABLE"
    },
    {
        "name": "batch_loss",
        "type": "FLOAT",
        "mode": "NULLABLE"
    },
    {
        "name": "epoch_num",
        "type": "INTEGER",
        "mode": "NULLABLE"
    },
    {
        "name": "epoch_len",
        "type": "INTEGER",
        "mode": "NULLABLE"
    },
    {
        "name": "epoch_loss",
        "type": "FLOAT",
        "mode": "NULLABLE"
    }
]